[{"ID":"1902","BXIMG":"/upload/images/546d699d652fc.jpg","JG":"4900","YHJG":"4400","LCSJ":"周一至周五","LOGOPIC":"/upload/images/jiaxiaoLogo/logo_yd.gif","JXNAME":"远大驾校","BXMC":"一至五直通车班","CXMC":"爱丽舍","JZLX":"C1","TSFWID":"8,3,1,7,4,2"},{"ID":"1907","BXIMG":"/upload/images/546d699d652fc.jpg","JG":"5200","YHJG":"4700","LCSJ":"周一至周日","LOGOPIC":"/upload/images/jiaxiaoLogo/logo_yd.gif","JXNAME":"远大驾校","BXMC":"一至日计时班","CXMC":"爱丽舍","JZLX":"C1","TSFWID":"8,3,1,7,4,2"},{"ID":"1912","BXIMG":"/upload/images/546d699d652fc.jpg","JG":"5600","YHJG":"5100","LCSJ":"周一至周日","LOGOPIC":"/upload/images/jiaxiaoLogo/logo_yd.gif","JXNAME":"远大驾校","BXMC":"一至日直通车班","CXMC":"爱丽舍","JZLX":"C1","TSFWID":"8,3,1,7,4,2"},{"ID":"1917","BXIMG":"/upload/images/546d699d652fc.jpg","JG":"5600","YHJG":"5100","LCSJ":"周一至周日","LOGOPIC":"/upload/images/jiaxiaoLogo/logo_yd.gif","JXNAME":"远大驾校","BXMC":"一至日自动挡计时班","CXMC":"爱丽舍","JZLX":"C2","TSFWID":"8,3,1,7,4,2"},{"ID":"1920","BXIMG":"/upload/images/546d699d652fc.jpg","JG":"6600","YHJG":"6100","LCSJ":"周一至周日","LOGOPIC":"/upload/images/jiaxiaoLogo/logo_yd.gif","JXNAME":"远大驾校","BXMC":"私人定制班","CXMC":"爱丽舍","JZLX":"C2","TSFWID":"8,3,1,7,4,2"},{"ID":"2090","BXIMG":"http://www.xuechebu.com/upload/201510/14/201510141549026058.jpg","JG":"4600","YHJG":"4100","LCSJ":"周一至周五","LOGOPIC":"/upload/images/jiaxiaoLogo/logo_yd.gif","JXNAME":"远大驾校","BXMC":"一至五计时班","CXMC":"爱丽舍","JZLX":"C1","TSFWID":"8,3,1,7,4,2"}]
