[{"ID":"14809","JGID":"116001","LOGOPIC":"/upload/images/jiaxiaoLogo/logo_jl.gif","DHPIC":"","JXDZ":"门头沟区龙泉镇岳家坡村北","JXWEBSITE":"","JXSERVICETEL":"69845364","JXPOSITION":"","JXSTAR":"","JXGMID":"934","QYID":"1626","SFYBC":"1","BANERPIC":"","POSITIONPIC":"","JXBCTEL":"","JXNAME":"九龙驾校","JXFULLNAME":"九龙驾校","JJ":"<p>九龙驾校拥有各型性能良好的车辆提供教学，教练员是通过严格的考核，并持证上岗，属经验丰富、作风正派、有职业道德、责任心强的高级驾驶员执教。<br/>&nbsp;&nbsp;&nbsp; 九龙驾校始终坚持一次性收费，随到随学原则，如有特殊情况可采取上门服务，学校对行管人员及教练员有一系列之有效的管理制度。不允许对学员以任何名义摊派费用，学校对违章违纪的行为历来奉行严惩不怠的原则，力求给学员一个满意的答复。<br/>&nbsp;&nbsp;&nbsp; 九龙驾校以雄厚的师资力量、优越的办学条件、成功的办学经验、科学的教学管理、一流的服务质量赢得了广大学员及各界的好评。我们欢迎有志于汽车驾驭的朋友来学校报名学习。</p>","SFXJ":"1","JXSL":"","XLC":"","JXMJ":"","CLSJ":"","BCZL":"齐全","BCXLSL":"10条","KSCD":"九龙考试场","BXZZ":"一览山景、一流教学。","JXJJPIC":"css/img/zhaojiaxiao/lb2.png,css/img/banner_3.jpg,css/img/zhaojiaxiao/bg.png"}]
